mousechd/__init__.py
mousechd/__main__.py
mousechd/classifier/__init__.py
mousechd/classifier/augments.py
mousechd/classifier/datagens.py
mousechd/classifier/evaluate.py
mousechd/classifier/gradcam.py
mousechd/classifier/models.py
mousechd/classifier/train.py
mousechd/classifier/utils.py
mousechd/datasets/__init__.py
mousechd/datasets/preprocess.py
mousechd/datasets/resample.py
mousechd/datasets/utils.py
mousechd/run/__init__.py
mousechd/run/create_label_df.py
mousechd/run/explain.py
mousechd/run/postprocess_nnUNet.py
mousechd/run/prepare_nnUNet_data.py
mousechd/run/preprocess.py
mousechd/run/resample.py
mousechd/run/segment.py
mousechd/run/split_data.py
mousechd/run/test_clf.py
mousechd/run/train_clf.py
mousechd/run/viz3d_seg.py
mousechd/run/viz3d_stages.py
mousechd/run/viz3d_views.py
mousechd/run/viz_eda.py
mousechd/run/viz_grad.py
mousechd/run/viz_seg.py
mousechd/run/viz_stacks.py
mousechd/segmentation/__init__.py
mousechd/segmentation/segment.py
mousechd/segmentation/utils.py
mousechd/utils/__init__.py
mousechd/utils/analyzer.py
mousechd/utils/tools.py
mousechd-0.0.6.dist-info/LICENSE
mousechd-0.0.6.dist-info/METADATA
mousechd-0.0.6.dist-info/WHEEL
mousechd-0.0.6.dist-info/entry_points.txt
mousechd-0.0.6.dist-info/top_level.txt
mousechd-0.0.6.dist-info/RECORD
