Metadata-Version: 2.1
Name: mousechd
Version: 0.0.6
Summary: Segmenting hearts and screening congenital heart diseases in mice
Home-page: https://github.com/hnguyentt/MouseCHD
Author: Hoa Nguyen
Author-email: ntthoa.uphcm@gmail.com
License: MIT
Keywords: deep learning,image segmentation,image classification,medical image analysis,mousechd
Classifier: Development Status :: 2 - Pre-Alpha
Classifier: Intended Audience :: Developers
Classifier: Intended Audience :: Science/Research
Classifier: Intended Audience :: Healthcare Industry
Classifier: Programming Language :: Python :: 3
Classifier: License :: OSI Approved :: MIT License
Classifier: Topic :: Scientific/Engineering :: Artificial Intelligence
Classifier: Topic :: Scientific/Engineering :: Image Recognition
Classifier: Topic :: Scientific/Engineering :: Medical Science Apps.
Requires-Python: >=3.9
License-File: LICENSE
Requires-Dist: opencv-contrib-python-headless
Requires-Dist: SimpleITK
Requires-Dist: tifffile
Requires-Dist: matplotlib
Requires-Dist: seaborn
Requires-Dist: venn
Requires-Dist: pydicom
Requires-Dist: pynrrd
Requires-Dist: PyYAML
Requires-Dist: nnunet ==1.7.1
Requires-Dist: volumentations-3D
Requires-Dist: tensorflow ==2.14.0
Requires-Dist: brokenaxes
